{
  "project_info": {
    "project_number": "293615090255",
    "project_id": "coyotefree-bc54d",
    "storage_bucket": "coyotefree-bc54d.firebasestorage.app"
  },
  "client": [
    {
      "client_info": {
        "mobilesdk_app_id": "1:293615090255:android:6321ec350c6fb5a94a883a",
        "android_client_info": {
          "package_name": "velocity.labs.coyotefree"
        }
      },
      "oauth_client": [],
      "api_key": [
        {
          "current_key": "AIzaSyA0j8dal3OavRa3WX3S3HJyhyEvWPhWmeY"
        }
      ],
      "services": {
        "appinvite_service": {
          "other_platform_oauth_client": []
        }
      }
    }
  ],
  "configuration_version": "1"
}